<?xml version="1.0"?>
<source xmlns="http://xml.phpdox.net/token">
  <file xmlns="http://xml.phpdox.net/src" path="/home/will/Desktop/Project/server_side" file="course_grade.php" realpath="/home/will/Desktop/Project/server_side/course_grade.php" size="583" time="2016-11-21T21:24:06+00:00" unixtime="1479763446" sha1="3e519b5a848991aa3d4f4c9c0e286ee6ff803012" relative="course_grade.php"/>
  <line no="1">
    <token name="T_OPEN_TAG">&lt;?php</token>
  </line>
  <line no="2"/>
  <line no="3">
    <token name="T_FUNCTION">function</token>
    <token name="T_WHITESPACE"> </token>
    <token name="T_STRING">connection</token>
    <token name="T_PHPDOX_OPEN_BRACKET">(</token>
    <token name="T_PHPDOX_CLOSE_BRACKET">)</token>
    <token name="T_PHPDOX_OPEN_CURLY">{</token>
  </line>
  <line no="4"/>
  <line no="5">
    <token name="T_WHITESPACE">  </token>
    <token name="T_VARIABLE">$servername</token>
    <token name="T_WHITESPACE"> </token>
    <token name="T_PHPDOX_EQUAL">=</token>
    <token name="T_WHITESPACE"> </token>
    <token name="T_CONSTANT_ENCAPSED_STRING">"localhost"</token>
    <token name="T_PHPDOX_SEMICOLON">;</token>
  </line>
  <line no="6">
    <token name="T_WHITESPACE">  </token>
    <token name="T_VARIABLE">$username</token>
    <token name="T_WHITESPACE"> </token>
    <token name="T_PHPDOX_EQUAL">=</token>
    <token name="T_WHITESPACE"> </token>
    <token name="T_CONSTANT_ENCAPSED_STRING">"Wei"</token>
    <token name="T_PHPDOX_SEMICOLON">;</token>
  </line>
  <line no="7">
    <token name="T_WHITESPACE">  </token>
    <token name="T_VARIABLE">$password</token>
    <token name="T_WHITESPACE"> </token>
    <token name="T_PHPDOX_EQUAL">=</token>
    <token name="T_WHITESPACE"> </token>
    <token name="T_CONSTANT_ENCAPSED_STRING">"123456"</token>
    <token name="T_PHPDOX_SEMICOLON">;</token>
  </line>
  <line no="8"/>
  <line no="9">
    <token name="T_WHITESPACE">  </token>
    <token name="T_COMMENT">// Create connection</token>
  </line>
  <line no="10">
    <token name="T_WHITESPACE">  </token>
    <token name="T_VARIABLE">$conn</token>
    <token name="T_WHITESPACE"> </token>
    <token name="T_PHPDOX_EQUAL">=</token>
    <token name="T_WHITESPACE"> </token>
    <token name="T_NEW">new</token>
    <token name="T_WHITESPACE"> </token>
    <token name="T_STRING">mysqli</token>
    <token name="T_PHPDOX_OPEN_BRACKET">(</token>
    <token name="T_VARIABLE">$servername</token>
    <token name="T_PHPDOX_COMMA">,</token>
    <token name="T_WHITESPACE"> </token>
    <token name="T_VARIABLE">$username</token>
    <token name="T_PHPDOX_COMMA">,</token>
    <token name="T_WHITESPACE"> </token>
    <token name="T_VARIABLE">$password</token>
    <token name="T_PHPDOX_CLOSE_BRACKET">)</token>
    <token name="T_PHPDOX_SEMICOLON">;</token>
  </line>
  <line no="11"/>
  <line no="12">
    <token name="T_WHITESPACE">  </token>
    <token name="T_COMMENT">// Check connection</token>
  </line>
  <line no="13">
    <token name="T_WHITESPACE">  </token>
    <token name="T_IF">if</token>
    <token name="T_WHITESPACE"> </token>
    <token name="T_PHPDOX_OPEN_BRACKET">(</token>
    <token name="T_VARIABLE">$conn</token>
    <token name="T_OBJECT_OPERATOR">-&gt;</token>
    <token name="T_STRING">connect_error</token>
    <token name="T_PHPDOX_CLOSE_BRACKET">)</token>
    <token name="T_WHITESPACE"> </token>
    <token name="T_PHPDOX_OPEN_CURLY">{</token>
  </line>
  <line no="14">
    <token name="T_WHITESPACE">      </token>
    <token name="T_EXIT">die</token>
    <token name="T_PHPDOX_OPEN_BRACKET">(</token>
    <token name="T_CONSTANT_ENCAPSED_STRING">"Connection failed: "</token>
    <token name="T_WHITESPACE"> </token>
    <token name="T_PHPDOX_DOT">.</token>
    <token name="T_WHITESPACE"> </token>
    <token name="T_VARIABLE">$conn</token>
    <token name="T_OBJECT_OPERATOR">-&gt;</token>
    <token name="T_STRING">connect_error</token>
    <token name="T_PHPDOX_CLOSE_BRACKET">)</token>
    <token name="T_PHPDOX_SEMICOLON">;</token>
  </line>
  <line no="15">
    <token name="T_WHITESPACE">  </token>
    <token name="T_PHPDOX_CLOSE_CURLY">}</token>
  </line>
  <line no="16">
    <token name="T_WHITESPACE">  </token>
    <token name="T_ECHO">echo</token>
    <token name="T_WHITESPACE"> </token>
    <token name="T_CONSTANT_ENCAPSED_STRING">"Connected successfully\n"</token>
    <token name="T_PHPDOX_SEMICOLON">;</token>
  </line>
  <line no="17"/>
  <line no="18">
    <token name="T_WHITESPACE">  </token>
    <token name="T_RETURN">return</token>
    <token name="T_WHITESPACE"> </token>
    <token name="T_VARIABLE">$conn</token>
    <token name="T_PHPDOX_SEMICOLON">;</token>
  </line>
  <line no="19">
    <token name="T_PHPDOX_CLOSE_CURLY">}</token>
  </line>
  <line no="20"/>
  <line no="21">
    <token name="T_FUNCTION">function</token>
    <token name="T_WHITESPACE"> </token>
    <token name="T_STRING">get_grade</token>
    <token name="T_PHPDOX_OPEN_BRACKET">(</token>
    <token name="T_VARIABLE">$conn</token>
    <token name="T_PHPDOX_CLOSE_BRACKET">)</token>
    <token name="T_PHPDOX_OPEN_CURLY">{</token>
  </line>
  <line no="22"/>
  <line no="23">
    <token name="T_WHITESPACE">  </token>
    <token name="T_VARIABLE">$sql1</token>
    <token name="T_WHITESPACE"> </token>
    <token name="T_PHPDOX_EQUAL">=</token>
    <token name="T_WHITESPACE"> </token>
    <token name="T_CONSTANT_ENCAPSED_STRING">""</token>
    <token name="T_PHPDOX_SEMICOLON">;</token>
  </line>
  <line no="24">
    <token name="T_WHITESPACE">  </token>
    <token name="T_VARIABLE">$grade_array</token>
    <token name="T_PHPDOX_SEMICOLON">;</token>
  </line>
  <line no="25">
    <token name="T_WHITESPACE">  </token>
    <token name="T_IF">if</token>
    <token name="T_WHITESPACE"> </token>
    <token name="T_PHPDOX_OPEN_BRACKET">(</token>
    <token name="T_VARIABLE">$conn</token>
    <token name="T_OBJECT_OPERATOR">-&gt;</token>
    <token name="T_STRING">query</token>
    <token name="T_PHPDOX_OPEN_BRACKET">(</token>
    <token name="T_VARIABLE">$sql1</token>
    <token name="T_PHPDOX_CLOSE_BRACKET">)</token>
    <token name="T_WHITESPACE"> </token>
    <token name="T_IS_IDENTICAL">===</token>
    <token name="T_WHITESPACE"> </token>
    <token name="T_STRING">TRUE</token>
    <token name="T_PHPDOX_CLOSE_BRACKET">)</token>
    <token name="T_WHITESPACE"> </token>
    <token name="T_PHPDOX_OPEN_CURLY">{</token>
  </line>
  <line no="26">
    <token name="T_WHITESPACE">      </token>
    <token name="T_ECHO">echo</token>
    <token name="T_WHITESPACE"> </token>
    <token name="T_CONSTANT_ENCAPSED_STRING">"get grade\n"</token>
    <token name="T_PHPDOX_SEMICOLON">;</token>
  </line>
  <line no="27">
    <token name="T_WHITESPACE">      </token>
    <token name="T_RETURN">return</token>
    <token name="T_WHITESPACE"> </token>
    <token name="T_VARIABLE">$grade_array</token>
    <token name="T_PHPDOX_SEMICOLON">;</token>
  </line>
  <line no="28">
    <token name="T_WHITESPACE">  </token>
    <token name="T_PHPDOX_CLOSE_CURLY">}</token>
    <token name="T_WHITESPACE"> </token>
    <token name="T_ELSE">else</token>
    <token name="T_WHITESPACE"> </token>
    <token name="T_PHPDOX_OPEN_CURLY">{</token>
  </line>
  <line no="29">
    <token name="T_WHITESPACE">      </token>
    <token name="T_ECHO">echo</token>
    <token name="T_WHITESPACE"> </token>
    <token name="T_CONSTANT_ENCAPSED_STRING">"Error creating database: "</token>
    <token name="T_WHITESPACE"> </token>
    <token name="T_PHPDOX_DOT">.</token>
    <token name="T_WHITESPACE"> </token>
    <token name="T_VARIABLE">$conn</token>
    <token name="T_OBJECT_OPERATOR">-&gt;</token>
    <token name="T_STRING">error</token>
    <token name="T_PHPDOX_SEMICOLON">;</token>
  </line>
  <line no="30">
    <token name="T_WHITESPACE">  </token>
    <token name="T_PHPDOX_CLOSE_CURLY">}</token>
  </line>
  <line no="31">
    <token name="T_PHPDOX_CLOSE_CURLY">}</token>
  </line>
  <line no="32"/>
  <line no="33">
    <token name="T_CLOSE_TAG">?&gt;</token>
  </line>
  <line no="34"/>
  <line no="35">
    <token name="T_INLINE_HTML">}</token>
  </line>
  <line no="36"/>
</source>
